pytrol/__init__.py
pytrol-0.1.0.dist-info/LICENSE
pytrol-0.1.0.dist-info/METADATA
pytrol-0.1.0.dist-info/WHEEL
pytrol-0.1.0.dist-info/top_level.txt
pytrol-0.1.0.dist-info/RECORD
