Metadata-Version: 2.1
Name: pytrol
Version: 0.1.0
Summary: easy to use Linux process managment in python
Home-page: https://github.com/daehruoydeef/pytrol
Author: daehruoydeef (Oskar)
Author-email: author@nodata.com
License: UNKNOWN
Platform: UNKNOWN
Classifier: Programming Language :: Python :: 3
Classifier: License :: OSI Approved :: MIT License
Classifier: Operating System :: OS Independent
